fixfmt/__init__.py
fixfmt/_ext.cpython-37m-darwin.so
fixfmt/npfmt.py
fixfmt/pandas.py
fixfmt/table.py
fixfmt/tbl.py
fixfmt/lib/__init__.py
fixfmt/lib/ansi.py
fixfmt/lib/box.py
fixfmt/lib/container.py
fixfmt/test/test_bool.py
fixfmt/test/test_choose_formatter.py
fixfmt/test/test_npfmt.py
fixfmt/test/test_number.py
fixfmt/test/test_string.py
fixfmt/test/test_table.py
fixfmt/test/test_text_functions.py
fixfmt/test/test_time.py
fixfmt-0.12.0.dist-info/LICENSE
fixfmt-0.12.0.dist-info/METADATA
fixfmt-0.12.0.dist-info/WHEEL
fixfmt-0.12.0.dist-info/top_level.txt
fixfmt-0.12.0.dist-info/RECORD
