Metadata-Version: 2.1
Name: fixfmt
Version: 0.12.0
Summary: fixed-width formatters for C++ and Python
Home-page: https://github.com/alexhsamuel/fixfmt
Author: Alex Samuel
Author-email: alexhsamuel@gmail.com
License: Apache 2.0
Keywords: formatting,tables
Platform: UNKNOWN
Classifier: Development Status :: 4 - Beta
Classifier: Intended Audience :: Developers
Classifier: License :: OSI Approved :: Apache Software License
Classifier: Programming Language :: Python :: 3
Classifier: Programming Language :: Python :: 3.6
